odoo/addons/edi_webservice_oca/README.rst
odoo/addons/edi_webservice_oca/__init__.py
odoo/addons/edi_webservice_oca/__manifest__.py
odoo/addons/edi_webservice_oca/components/__init__.py
odoo/addons/edi_webservice_oca/components/send.py
odoo/addons/edi_webservice_oca/demo/edi_backend.xml
odoo/addons/edi_webservice_oca/i18n/edi_webservice.pot
odoo/addons/edi_webservice_oca/i18n/edi_webservice_oca.pot
odoo/addons/edi_webservice_oca/i18n/it.po
odoo/addons/edi_webservice_oca/models/__init__.py
odoo/addons/edi_webservice_oca/models/edi_backend.py
odoo/addons/edi_webservice_oca/readme/CONFIGURE.md
odoo/addons/edi_webservice_oca/readme/CONTRIBUTORS.md
odoo/addons/edi_webservice_oca/readme/DESCRIPTION.md
odoo/addons/edi_webservice_oca/security/ir.model.access.csv
odoo/addons/edi_webservice_oca/static/description/icon.png
odoo/addons/edi_webservice_oca/static/description/index.html
odoo/addons/edi_webservice_oca/tests/__init__.py
odoo/addons/edi_webservice_oca/tests/common.py
odoo/addons/edi_webservice_oca/tests/test_backend.py
odoo/addons/edi_webservice_oca/tests/test_send.py
odoo/addons/edi_webservice_oca/views/edi_backend.xml
odoo_addon_edi_webservice_oca-18.0.1.0.1.dist-info/METADATA
odoo_addon_edi_webservice_oca-18.0.1.0.1.dist-info/WHEEL
odoo_addon_edi_webservice_oca-18.0.1.0.1.dist-info/top_level.txt
odoo_addon_edi_webservice_oca-18.0.1.0.1.dist-info/RECORD
